trame/__init__.py
trame/modules/__init__.py
trame/modules/vuetify.py
trame/modules/vuetify2.py
trame/modules/vuetify3.py
trame/modules/vuetify3_lab.py
trame/ui/__init__.py
trame/ui/vuetify.py
trame/ui/vuetify2.py
trame/ui/vuetify3.py
trame/widgets/__init__.py
trame/widgets/vuetify.py
trame/widgets/vuetify2.py
trame/widgets/vuetify3.py
trame_vuetify/LICENSE
trame_vuetify/__init__.py
trame_vuetify/module/__init__.py
trame_vuetify/module/vue2.py
trame_vuetify/module/vue3.py
trame_vuetify/module/vue3_lab.py
trame_vuetify/module/roboto/KFOMCnqEu92Fr1ME7kSn66aGLdTylUAMQXC89YmC2DPNWuaabVmUiA8.ttf
trame_vuetify/module/roboto/KFOMCnqEu92Fr1ME7kSn66aGLdTylUAMQXC89YmC2DPNWub2bVmUiA8.ttf
trame_vuetify/module/roboto/KFOMCnqEu92Fr1ME7kSn66aGLdTylUAMQXC89YmC2DPNWubEbVmUiA8.ttf
trame_vuetify/module/roboto/roboto.css
trame_vuetify/module/vue2-serve/trame-vuetify.common.js
trame_vuetify/module/vue2-serve/trame-vuetify.css
trame_vuetify/module/vue2-serve/trame-vuetify.umd.js
trame_vuetify/module/vue2-serve/trame-vuetify.umd.min.js
trame_vuetify/module/vue2-serve/fonts/materialdesignicons-webfont.0766edc9.eot
trame_vuetify/module/vue2-serve/fonts/materialdesignicons-webfont.714a4eee.ttf
trame_vuetify/module/vue2-serve/fonts/materialdesignicons-webfont.e659bf56.woff
trame_vuetify/module/vue2-serve/fonts/materialdesignicons-webfont.fbaef2a9.woff2
trame_vuetify/module/vue2-serve/fonts/roboto-latin-100.539f0a96.woff2
trame_vuetify/module/vue2-serve/fonts/roboto-latin-100.5ba994da.woff
trame_vuetify/module/vue2-serve/fonts/roboto-latin-100italic.41ba6421.woff2
trame_vuetify/module/vue2-serve/fonts/roboto-latin-100italic.d61e7e8b.woff
trame_vuetify/module/vue2-serve/fonts/roboto-latin-300.4d8f8086.woff2
trame_vuetify/module/vue2-serve/fonts/roboto-latin-300.6c1bc461.woff
trame_vuetify/module/vue2-serve/fonts/roboto-latin-300italic.3a529751.woff
trame_vuetify/module/vue2-serve/fonts/roboto-latin-300italic.45164643.woff2
trame_vuetify/module/vue2-serve/fonts/roboto-latin-400.1e2d4d3a.woff2
trame_vuetify-3.2.0.dist-info/licenses/LICENSE
trame_vuetify-3.2.0.dist-info/METADATA
trame_vuetify-3.2.0.dist-info/WHEEL
trame_vuetify-3.2.0.dist-info/top_level.txt
trame_vuetify-3.2.0.dist-info/RECORD
